httpq/__init__.py
httpq/httpq.py
httpq-1.2.0.dist-info/AUTHORS
httpq-1.2.0.dist-info/LICENSE
httpq-1.2.0.dist-info/METADATA
httpq-1.2.0.dist-info/WHEEL
httpq-1.2.0.dist-info/pbr.json
httpq-1.2.0.dist-info/top_level.txt
httpq-1.2.0.dist-info/RECORD
